pystub/__init__.py
pystub/_cli.py
pystub/_cli_core.py
pystub/_cli_modules/__init__.py
pystub/_cli_modules/section.py
pystub/_common_utils.py
pystub/_logger.py
pystub-0.2.1.dist-info/LICENSE
pystub-0.2.1.dist-info/WHEEL
pystub-0.2.1.dist-info/METADATA
pystub-0.2.1.dist-info/RECORD
