Metadata-Version: 2.1
Name: pystub
Version: 0.2.1
Summary: Python Stub
License: Apache 2.0
Author: tonynv
Author-email: avattathil@gmail.com
Requires-Python: >=3.10,<4.0
Classifier: License :: Other/Proprietary License
Classifier: Programming Language :: Python :: 3
Classifier: Programming Language :: Python :: 3.10
Classifier: Programming Language :: Python :: 3.11
Requires-Dist: requests (==2.28.1)
Requires-Dist: setuptools (==65.3.0)
